onegov.event-1.2.0-py3.6-nspkg.pth
onegov/event/.gitignore
onegov/event/__init__.py
onegov/event/cli.py
onegov/event/upgrade.py
onegov/event/collections/__init__.py
onegov/event/collections/events.py
onegov/event/collections/occurrences.py
onegov/event/models/__init__.py
onegov/event/models/event.py
onegov/event/models/mixins.py
onegov/event/models/occurrence.py
onegov/event/tests/conftest.py
onegov/event/tests/test_cli.py
onegov/event/tests/test_collections.py
onegov/event/tests/test_models.py
onegov/event/tests/test_utils.py
onegov/event/tests/fixtures/event.jpg
onegov/event/tests/fixtures/event.png
onegov/event/tests/fixtures/guidle.xml
onegov/event/utils/__init__.py
onegov/event/utils/guidle.py
onegov/event/utils/utils.py
onegov.event-1.2.0.dist-info/METADATA
onegov.event-1.2.0.dist-info/WHEEL
onegov.event-1.2.0.dist-info/entry_points.txt
onegov.event-1.2.0.dist-info/namespace_packages.txt
onegov.event-1.2.0.dist-info/top_level.txt
onegov.event-1.2.0.dist-info/RECORD
