Metadata-Version: 2.1
Name: onegov.event
Version: 1.2.0
Summary: Calendar of events for OneGov.
Home-page: http://github.com/OneGov/onegov.event
Author: Seantis GmbH
Author-email: info@seantis.ch
License: GPLv2
Platform: any
Classifier: Intended Audience :: Developers
Classifier: Programming Language :: Python :: 3 :: Only
Classifier: Programming Language :: Python :: 3.6
Classifier: Programming Language :: Python :: 3.7
Classifier: Topic :: Software Development :: Libraries :: Python Modules
Classifier: License :: OSI Approved :: GNU General Public License v2 (GPLv2)
Requires-Python: >=3.6
Requires-Dist: bleach
Requires-Dist: icalendar (>=4.0.3)
Requires-Dist: lxml
Requires-Dist: onegov.core (>=0.4.0)
Requires-Dist: onegov.file
Requires-Dist: onegov.gis
Requires-Dist: onegov.search
Requires-Dist: onegov.server
Requires-Dist: python-dateutil (>=2.7.3)
Requires-Dist: requests
Requires-Dist: sedate
Provides-Extra: test
Requires-Dist: coverage ; extra == 'test'
Requires-Dist: freezegun ; extra == 'test'
Requires-Dist: onegov-testing ; extra == 'test'
Requires-Dist: pytest ; extra == 'test'
